fdflim/__init__.py
fdFLIM-0.5.1.dist-info/LICENSE
fdFLIM-0.5.1.dist-info/METADATA
fdFLIM-0.5.1.dist-info/WHEEL
fdFLIM-0.5.1.dist-info/top_level.txt
fdFLIM-0.5.1.dist-info/RECORD
