Metadata-Version: 2.1
Name: fdFLIM
Version: 0.5.1
Summary: Several functions for working with frequency domain FLIM data.
Home-page: https://github.com/rharkes/fdFLIM-py
Author: Rolf Harkes
Author-email: rolf@harkes.nu
License: UNKNOWN
Platform: UNKNOWN
Classifier: Programming Language :: Python :: 3
Classifier: License :: OSI Approved :: GNU General Public License v3 (GPLv3)
Classifier: Operating System :: OS Independent
Requires-Python: >=3.7
